{
  "title": "How to watch the 2026 NFL Pro Bowl Games: TV channel, streaming info, start time and more",
  "category": "general",
  "sources": [
    {
      "name": "Yahoo Sports NFL",
      "title": "How to watch the 2026 NFL Pro Bowl Games: TV channel, streaming info, start time and more",
      "description": "The NFL Pro Bowl Games are this Tuesday, here's where you can watch all the festivities live.",
      "url": "https://sports.yahoo.com/nfl/article/how-to-watch-the-2026-nfl-pro-bowl-games-tv-channel-streaming-info-start-time-and-more-164517007.html"
    }
  ],
  "keywords": [
    "watch",
    "2026",
    "pro",
    "bowl",
    "games",
    "channel",
    "streaming",
    "info",
    "start",
    "time",
    "this",
    "tuesday",
    "heres",
    "you",
    "festivities",
    "live"
  ],
  "hash": "b022b4cb2a50aeab",
  "queuedAt": "2026-02-03T02:28:05.363Z"
}