{
  "title": "NFL quickly changes its tune on prediction markets",
  "category": "general",
  "sources": [
    {
      "name": "Pro Football Talk",
      "title": "NFL quickly changes its tune on prediction markets",
      "description": "The NFL hated legalized gambling, until it didn't.",
      "url": "https://www.nbcsports.com/nfl/profootballtalk/rumor-mill/news/nfl-quickly-changes-its-tune-on-prediction-markets"
    }
  ],
  "keywords": [
    "quickly",
    "changes",
    "its",
    "tune",
    "prediction",
    "markets",
    "hated",
    "legalized",
    "gambling",
    "until",
    "didnt"
  ],
  "hash": "1f8d8c9190de7227",
  "queuedAt": "2026-02-06T07:00:13.603Z"
}