{
  "title": "NFL announces return to Mexico with International Series Game in Mexico City for next three seasons",
  "category": "general",
  "sources": [
    {
      "name": "CBS Sports NFL",
      "title": "NFL announces return to Mexico with International Series Game in Mexico City for next three seasons",
      "description": "After a four-year hiatus, the NFL will return to Mexico with a game next season",
      "url": "https://www.cbssports.com/nfl/news/nfl-international-series-game-mexico-city/"
    }
  ],
  "keywords": [
    "announces",
    "return",
    "mexico",
    "international",
    "series",
    "city",
    "next",
    "three",
    "seasons",
    "fouryear",
    "hiatus"
  ],
  "hash": "48cb11bfdf7583f9",
  "queuedAt": "2026-02-03T02:28:08.233Z"
}