{
  "title": "Records that could fall in Super Bowl 2026: Is Jerry Rice&#039;s iconic mark about to fall?",
  "category": "superbowl",
  "sources": [
    {
      "name": "CBS Sports NFL",
      "title": "Records that could fall in Super Bowl 2026: Is Jerry Rice&#039;s iconic mark about to fall?",
      "description": "Rice&#039;s record is one of several long-standing marks that could fall this year",
      "url": "https://www.cbssports.com/nfl/news/records-that-could-fall-in-super-bowl-2026-jerry-rice/"
    }
  ],
  "keywords": [
    "records",
    "that",
    "fall",
    "super",
    "bowl",
    "2026",
    "jerry",
    "rice039s",
    "iconic",
    "mark",
    "about",
    "record",
    "one",
    "several",
    "longstanding",
    "marks",
    "this"
  ],
  "hash": "e592e20be312dd24",
  "queuedAt": "2026-02-02T06:08:59.489Z"
}