{
  "title": "How can I watch the Super Bowl online or without cable? Streaming info, start time and more",
  "category": "superbowl",
  "sources": [
    {
      "name": "Yahoo Sports NFL",
      "title": "How can I watch the Super Bowl online or without cable? Streaming info, start time and more",
      "description": "Find out how to watch the 2026 Super Bowl without cable when it airs on Sunday, February 8.",
      "url": "https://sports.yahoo.com/nfl/article/how-can-i-watch-the-super-bowl-online-or-without-cable-streaming-info-start-time-and-more-164555418.html"
    }
  ],
  "keywords": [
    "watch",
    "super",
    "bowl",
    "online",
    "without",
    "cable",
    "streaming",
    "info",
    "start",
    "time",
    "find",
    "out",
    "2026",
    "airs",
    "sunday",
    "february"
  ],
  "hash": "a8bcb428450883fa",
  "queuedAt": "2026-02-05T18:55:21.392Z"
}