{
  "title": "Julian Love thought he’d be with Giants ‘longer’ — but things more than worked out with Seahawks",
  "category": "general",
  "sources": [
    {
      "name": "Yahoo Sports NFL",
      "title": "Julian Love thought he’d be with Giants ‘longer’ — but things more than worked out with Seahawks",
      "description": "Julian Love did not know if he would end his NFL career where he began it, with the Giants.",
      "url": "https://sports.yahoo.com/articles/julian-love-thought-d-giants-022111138.html"
    }
  ],
  "keywords": [
    "julian",
    "love",
    "thought",
    "hed",
    "giants",
    "longer",
    "things",
    "worked",
    "out",
    "seahawks",
    "know",
    "end",
    "his",
    "career",
    "began"
  ],
  "hash": "7a7d99e8971f819a",
  "queuedAt": "2026-02-07T12:57:27.718Z"
}