{
  "title": "Super Bowl 2026 weather forecast: Conditions for Patriots vs. Seahawks at Levi's Stadium",
  "category": "superbowl",
  "sources": [
    {
      "name": "CBS Sports NFL",
      "title": "Super Bowl 2026 weather forecast: Conditions for Patriots vs. Seahawks at Levi&#039;s Stadium",
      "description": "Here are the conditions Seattle and New England will be playing in during Super Bowl LX",
      "url": "https://www.cbssports.com/nfl/news/super-bowl-2026-weather-forecast-patriots-seahawks-levi-stadium/"
    }
  ],
  "keywords": [
    "super",
    "bowl",
    "2026",
    "weather",
    "forecast",
    "conditions",
    "patriots",
    "seahawks",
    "levi039s",
    "stadium",
    "seattle",
    "new",
    "england",
    "playing"
  ],
  "hash": "8220a8ec40f6db12",
  "queuedAt": "2026-02-05T18:55:23.422Z"
}