{
  "title": "2025 Season In Review: Grading Out The First-Year Head Coaches",
  "category": "coaching",
  "sources": [
    {
      "name": "Yahoo Sports NFL",
      "title": "2025 Season In Review: Grading Out The First-Year Head Coaches",
      "description": "The 2025 NFL regular season has come to a close. After Year 1, how do all seven first-year head coaches stack up?",
      "url": "https://sports.yahoo.com/articles/2025-season-review-grading-first-210000665.html"
    }
  ],
  "keywords": [
    "2025",
    "review",
    "grading",
    "out",
    "firstyear",
    "head",
    "coaches",
    "regular",
    "come",
    "close",
    "seven",
    "stack"
  ],
  "hash": "4807f732f909f539",
  "queuedAt": "2026-02-07T02:14:15.741Z"
}