{
  "title": "C.J. Ham Makes Retirement Official",
  "category": "player-news",
  "sources": [
    {
      "name": "Yahoo Sports NFL",
      "title": "C.J. Ham Makes Retirement Official",
      "description": "Congratulations to a career Viking",
      "url": "https://sports.yahoo.com/articles/c-j-ham-makes-retirement-003219304.html"
    }
  ],
  "keywords": [
    "ham",
    "makes",
    "retirement",
    "official",
    "congratulations",
    "career",
    "viking"
  ],
  "hash": "4cb3be85fdef5854",
  "queuedAt": "2026-02-04T02:22:57.221Z"
}