{
  "title": "Super Bowl Anytime Touchdown Scorer: Picks, Odds & Strategy",
  "category": "draft",
  "sources": [
    {
      "name": "Yahoo Sports NFL",
      "title": "Super Bowl Anytime Touchdown Scorer: Picks, Odds & Strategy",
      "description": "Get expert Super Bowl anytime touchdown scorer predictions, odds, strategy, and top player picks for Super Bowl 60. Learn how to bet smarter on this popular NFL prop.",
      "url": "https://sports.yahoo.com/articles/super-bowl-anytime-touchdown-scorer-192700785.html"
    }
  ],
  "keywords": [
    "super",
    "bowl",
    "anytime",
    "touchdown",
    "scorer",
    "picks",
    "odds",
    "strategy",
    "get",
    "expert",
    "predictions",
    "top",
    "learn",
    "bet",
    "smarter",
    "this",
    "popular",
    "prop"
  ],
  "hash": "763db7bb0516ef28",
  "queuedAt": "2026-02-07T02:14:15.432Z"
}