{
  "title": "Where Seahawks' Jaxon Smith-Njigba lands on 2025 wide receiver rankings, any Patriots make list?",
  "category": "general",
  "sources": [
    {
      "name": "CBS Sports NFL",
      "title": "Where Seahawks&#039; Jaxon Smith-Njigba lands on 2025 wide receiver rankings, any Patriots make list?",
      "description": "A look at the top 15 NFL wide receivers at the conclusion of the 2025 season while looking ahead to 2026",
      "url": "https://www.cbssports.com/nfl/news/seahawks-jaxon-smith-njigba-wide-receiver-rankings-patriots-super-bowl-2026/"
    }
  ],
  "keywords": [
    "seahawks039",
    "jaxon",
    "smithnjigba",
    "lands",
    "2025",
    "wide",
    "receiver",
    "rankings",
    "any",
    "patriots",
    "make",
    "list",
    "look",
    "top",
    "receivers",
    "conclusion",
    "while",
    "looking",
    "ahead",
    "2026"
  ],
  "hash": "fc3dbfb4d938eb74",
  "queuedAt": "2026-02-04T18:56:19.278Z"
}