{
  "title": "Matt Stafford confirms he’s returning to Rams in MVP speech",
  "category": "coaching",
  "sources": [
    {
      "name": "Yahoo Sports NFL",
      "title": "Matt Stafford confirms he’s returning to Rams in MVP speech",
      "description": "Rams’ Matthew Stafford wins MVP and confirms he will play in 2026",
      "url": "https://sports.yahoo.com/articles/matt-stafford-confirms-returning-rams-040421028.html"
    }
  ],
  "keywords": [
    "matt",
    "stafford",
    "confirms",
    "hes",
    "returning",
    "rams",
    "mvp",
    "speech",
    "matthew",
    "wins",
    "play",
    "2026"
  ],
  "hash": "4ec1ae23fd465e1e",
  "queuedAt": "2026-02-06T07:00:09.988Z"
}