{
  "title": "Super Bowl Prop Bets: Odds and Expert Picks for Super Bowl LX",
  "category": "draft",
  "sources": [
    {
      "name": "Yahoo Sports NFL",
      "title": "Super Bowl Prop Bets: Odds and Expert Picks for Super Bowl LX",
      "description": "We share the most popular Super Bowl props and corresponding odds for Super Bowl 60, from the coin toss to game props.",
      "url": "https://sports.yahoo.com/articles/super-bowl-prop-bets-bets-165100253.html"
    }
  ],
  "keywords": [
    "super",
    "bowl",
    "prop",
    "bets",
    "odds",
    "expert",
    "picks",
    "share",
    "popular",
    "props",
    "corresponding",
    "coin",
    "toss"
  ],
  "hash": "da42db67976feea7",
  "queuedAt": "2026-02-02T06:08:57.511Z"
}