{
  "title": "Steelers hire former Commanders defensive coordinator to assistant head coach role",
  "category": "coaching",
  "sources": [
    {
      "name": "Yahoo Sports NFL",
      "title": "Steelers hire former Commanders defensive coordinator to assistant head coach role",
      "description": "Pittsburgh adds familiar face to McCarthy as Washington DC joins staff",
      "url": "https://sports.yahoo.com/articles/steelers-hire-former-commanders-defensive-212800431.html"
    }
  ],
  "keywords": [
    "steelers",
    "hire",
    "former",
    "commanders",
    "defensive",
    "coordinator",
    "assistant",
    "head",
    "coach",
    "role",
    "pittsburgh",
    "adds",
    "familiar",
    "face",
    "mccarthy",
    "washington",
    "joins",
    "staff"
  ],
  "hash": "021097fdd3c44f5e",
  "queuedAt": "2026-02-05T02:24:28.542Z"
}