{
  "title": "Kliff Kingsbury to join Rams coaching staff",
  "category": "coaching",
  "sources": [
    {
      "name": "Pro Football Talk",
      "title": "Kliff Kingsbury to join Rams coaching staff",
      "description": "Kingsbury is headed back to the NFC West after parting ways with the Commanders last month.",
      "url": "https://www.nbcsports.com/nfl/profootballtalk/rumor-mill/news/kliff-kingsbury-to-join-rams-coaching-staff"
    }
  ],
  "keywords": [
    "kliff",
    "kingsbury",
    "join",
    "rams",
    "coaching",
    "staff",
    "headed",
    "back",
    "nfc",
    "west",
    "parting",
    "ways",
    "commanders",
    "last",
    "month"
  ],
  "hash": "4b1b5b5bd0eca857",
  "queuedAt": "2026-02-07T06:49:01.557Z"
}